{
    "escape": [
        {
            "nombre": "ManoloGamer",
            "puntos": 1120,
            "tiempo": 45,
            "resultado": "ganaste"
        },
        {
            "nombre": "a",
            "puntos": 320,
            "tiempo": 19,
            "resultado": "ganaste"
        }
    ],
    "cazador": [
        {
            "nombre": "NovatoMC",
            "puntos": 8400,
            "tiempo": 150,
            "resultado": "ganaste"
        },
        {
            "nombre": "a",
            "puntos": 5400,
            "tiempo": 54,
            "resultado": "ganaste"
        }
    ]
}